acdh_cfts_pyutils/__init__.py
acdh_cfts_pyutils-0.2.dist-info/LICENSE
acdh_cfts_pyutils-0.2.dist-info/METADATA
acdh_cfts_pyutils-0.2.dist-info/WHEEL
acdh_cfts_pyutils-0.2.dist-info/top_level.txt
acdh_cfts_pyutils-0.2.dist-info/RECORD
