Metadata-Version: 2.1
Name: acdh-cfts-pyutils
Version: 0.2
Summary: Python Package to interact with a dedicated Typesense Server and Collection
Home-page: https://github.com/acdh-oeaw/acdh-cfts-pyutils
Author: Peter Andorfer
Author-email: peter.andorfer@oeaw.ac.at
License: MIT
Platform: UNKNOWN
License-File: LICENSE
Requires-Dist: typesense (==0.14.0)
